feincms3_downloads/__init__.py
feincms3_downloads/plugins.py
feincms3_downloads/locale/de/LC_MESSAGES/django.mo
feincms3_downloads/locale/de/LC_MESSAGES/django.po
feincms3_downloads/templates/plugins/download.html
feincms3_images/__init__.py
feincms3_images/plugins.py
feincms3_images/locale/de/LC_MESSAGES/.django.po.swp
feincms3_images/locale/de/LC_MESSAGES/django.mo
feincms3_images/locale/de/LC_MESSAGES/django.po
feincms3_images/templates/plugins/download.html
feincms3_images-0.1.1.dist-info/DESCRIPTION.rst
feincms3_images-0.1.1.dist-info/METADATA
feincms3_images-0.1.1.dist-info/RECORD
feincms3_images-0.1.1.dist-info/WHEEL
feincms3_images-0.1.1.dist-info/metadata.json
feincms3_images-0.1.1.dist-info/top_level.txt
