Metadata-Version: 2.0
Name: feincms3-images
Version: 0.1.1
Summary: Images plugin for feincms3
Home-page: https://github.com/matthiask/feincms3-images/
Author: Matthias Kestenholz
Author-email: mk@feinheit.ch
License: MIT License
Platform: OS Independent
Classifier: Development Status :: 4 - Beta
Classifier: Environment :: Web Environment
Classifier: Framework :: Django
Classifier: Intended Audience :: Developers
Classifier: License :: OSI Approved :: BSD License
Classifier: Operating System :: OS Independent
Classifier: Programming Language :: Python
Classifier: Programming Language :: Python :: 3
Classifier: Topic :: Internet :: WWW/HTTP :: Dynamic Content
Classifier: Topic :: Software Development
Classifier: Topic :: Software Development :: Libraries :: Application Frameworks
Requires-Dist: django-versatileimagefield
